CHANGES.rst
LICENSE.txt
MANIFEST.in
README.rst
ZHW.png
bootstrap.py
buildout.cfg
setup.py
zeo.cfg
Products/__init__.py
Products/ZopeHealthWatcher/LICENSE.txt
Products/ZopeHealthWatcher/README.txt
Products/ZopeHealthWatcher/VERSION.txt
Products/ZopeHealthWatcher/__init__.py
Products/ZopeHealthWatcher/check_zope.py
Products/ZopeHealthWatcher/custom.py
Products/ZopeHealthWatcher/dumper.py
Products/ZopeHealthWatcher/modules.py
Products/ZopeHealthWatcher/template.html
Products/ZopeHealthWatcher/tests.py
ZopeHealthWatcher.egg-info/PKG-INFO
ZopeHealthWatcher.egg-info/SOURCES.txt
ZopeHealthWatcher.egg-info/dependency_links.txt
ZopeHealthWatcher.egg-info/entry_points.txt
ZopeHealthWatcher.egg-info/namespace_packages.txt
ZopeHealthWatcher.egg-info/not-zip-safe
ZopeHealthWatcher.egg-info/requires.txt
ZopeHealthWatcher.egg-info/top_level.txt