Metadata-Version: 1.1
Name: ZopeHealthWatcher
Version: 0.9.0
Summary: ZopeHealthWatcher allows you to monitor and debug the threads of a Zope application.
Home-page: https://github.com/collective/Products.ZopeHealthWatcher
Author: Tarek Ziade
Author-email: tarek@ziade.org
License: GPL
Keywords: Plone Zope monitoring
Platform: UNKNOWN
Classifier: Framework :: Plone
Classifier: Framework :: Zope2
Classifier: Framework :: Plone :: 3.3
Classifier: Framework :: Plone :: 4.0
Classifier: Framework :: Plone :: 4.1
Classifier: Framework :: Plone :: 4.2
Classifier: Framework :: Plone :: 4.3
Classifier: Framework :: Plone :: 5.0
Classifier: Programming Language :: Python
Classifier: Programming Language :: Python :: 2.4
Classifier: Programming Language :: Python :: 2.6
Classifier: Programming Language :: Python :: 2.7
Classifier: Topic :: Software Development :: Libraries :: Python Modules
Classifier: Topic :: System :: Monitoring
Classifier: License :: OSI Approved :: GNU General Public License v2 (GPLv2)
